README.md
setup.py
pynetoptix/__init__.py
pynetoptix.egg-info/PKG-INFO
pynetoptix.egg-info/SOURCES.txt
pynetoptix.egg-info/dependency_links.txt
pynetoptix.egg-info/top_level.txt
pynetoptix/core/__init__.py
pynetoptix/core/client.py
pynetoptix/core/config.py
pynetoptix/core/http.py
pynetoptix/services/__init__.py
pynetoptix/services/server_api.py
pynetoptix/services/system_api.py
pynetoptix/services/video_api.py