Metadata-Version: 1.1
Name: pynetoptix
Version: 0.0.7
Summary: A simple Python wrapper over NetworkOptix' HTTP API
Home-page: https://github.com/ImageIntelligence/pynetoptix
Author: David Vuong
Author-email: david@imageintellience.com
License: UNKNOWN
Platform: UNKNOWN
Classifier: Intended Audience :: Developers
Classifier: Topic :: Utilities
Classifier: Programming Language :: Python :: 3 :: Only
Classifier: Programming Language :: Python :: 3.5
Classifier: Programming Language :: Python :: 3.6
